gym_retro-0.5.5.dist-info/METADATA
gym_retro-0.5.5.dist-info/RECORD
gym_retro-0.5.5.dist-info/WHEEL
gym_retro-0.5.5.dist-info/top_level.txt
retro/VERSION.txt
retro/__init__.py
retro/_retro.cpython-36m-darwin.so
retro/cores.json
retro/data.py
retro/retro_env.py
retro/cores/genesis_plus_gx_libretro.dylib
retro/cores/stella_libretro.dylib
retro/data/Adventure-Atari2600/Start.state
retro/data/Adventure-Atari2600/data.json
retro/data/Adventure-Atari2600/metadata.json
retro/data/Adventure-Atari2600/rom.sha
retro/data/Adventure-Atari2600/scenario.json
retro/data/AirRaid-Atari2600/Start.state
retro/data/AirRaid-Atari2600/data.json
retro/data/AirRaid-Atari2600/metadata.json
retro/data/AirRaid-Atari2600/rom.sha
retro/data/AirRaid-Atari2600/scenario.json
retro/data/Airstriker-Genesis/Level1.state
retro/data/Airstriker-Genesis/data.json
retro/data/Airstriker-Genesis/metadata.json
retro/data/Airstriker-Genesis/rom.md
retro/data/Airstriker-Genesis/rom.sha
retro/data/Airstriker-Genesis/scenario.json
retro/data/Alien-Atari2600/Start.state
retro/data/Alien-Atari2600/data.json
retro/data/Alien-Atari2600/metadata.json
retro/data/Alien-Atari2600/rom.sha
retro/data/Alien-Atari2600/scenario.json
retro/data/AlienSoldier-Genesis/DefaultSettings.Level1.state
retro/data/AlienSoldier-Genesis/DefaultSettings.Level10.state
retro/data/AlienSoldier-Genesis/DefaultSettings.Level11.state
retro/data/AlienSoldier-Genesis/DefaultSettings.Level12.state
retro/data/AlienSoldier-Genesis/DefaultSettings.Level13.state
retro/data/AlienSoldier-Genesis/DefaultSettings.Level14.state
retro/data/AlienSoldier-Genesis/DefaultSettings.Level15.state
retro/data/AlienSoldier-Genesis/DefaultSettings.Level16.state
retro/data/AlienSoldier-Genesis/DefaultSettings.Level17.state
retro/data/AlienSoldier-Genesis/DefaultSettings.Level18.state
retro/data/AlienSoldier-Genesis/DefaultSettings.Level19.state
retro/data/AlienSoldier-Genesis/DefaultSettings.Level2.state
retro/data/AlienSoldier-Genesis/DefaultSettings.Level20.state
retro/data/AlienSoldier-Genesis/DefaultSettings.Level21.state
